mz_msisdn/__init__.py
mz_msisdn-0.0.1.dist-info/LICENCE
mz_msisdn-0.0.1.dist-info/METADATA
mz_msisdn-0.0.1.dist-info/WHEEL
mz_msisdn-0.0.1.dist-info/top_level.txt
mz_msisdn-0.0.1.dist-info/RECORD
