Metadata-Version: 2.1
Name: mz-msisdn
Version: 0.0.1
Summary: A small package to validate if a mozambican number is formated properly.
Home-page: https://github.com/paulocuambe/mz_msisdn
Author: Paulo Amosse Cuambe
Author-email: pamossecuambe@gmail.com
License: UNKNOWN
Platform: UNKNOWN
Classifier: Programming Language :: Python :: 3
Classifier: License :: OSI Approved :: MIT License
Classifier: Operating System :: OS Independent
Requires-Python: >=3.6
